{
  "_note": "Update this file manually when NBS/CBN release new data. Sources: nigerianstat.gov.ng and cbn.gov.ng",
  "updatedAt": "2026-07",
  "inflation": {
    "value": 15.91,
    "period": "June 2026",
    "source": "NBS",
    "sourceUrl": "https://www.nigerianstat.gov.ng/",
    "trend": "down"
  },
  "gdpPerCapita": {
    "value": 3.46,
    "unit": "percent YoY",
    "period": "Q1 2026",
    "source": "NBS",
    "sourceUrl": "https://www.nigerianstat.gov.ng/",
    "description": "Real GDP per capita growth rate"
  },
  "mpr": {
    "value": 26.5,
    "unit": "percent",
    "period": "May 2026",
    "source": "CBN",
    "sourceUrl": "https://www.cbn.gov.ng/",
    "description": "Monetary Policy Rate (policy anchor)"
  },
  "reserves": {
    "value": 51.86,
    "unit": "Billion USD",
    "period": "July 2026",
    "source": "CBN",
    "sourceUrl": "https://www.cbn.gov.ng/",
    "description": "Gross external/foreign reserves"
  },
  "fx": {
    "usd": 1380,
    "gbp": 1856,
    "eur": 1578,
    "period": "July 2026",
    "source": "NAFEM / CBN",
    "sourceUrl": "https://www.cbn.gov.ng/",
    "description": "Exchange rates: NGN per 1 unit of foreign currency"
  }
}
